pynexitec/__init__.py
pynexitec/tic_tac_toe.py
pynexitec-0.1.2.dist-info/licenses/LICENSE
pynexitec-0.1.2.dist-info/METADATA
pynexitec-0.1.2.dist-info/WHEEL
pynexitec-0.1.2.dist-info/top_level.txt
pynexitec-0.1.2.dist-info/RECORD
