Metadata-Version: 2.4
Name: pynexitec
Version: 0.1.2
Summary: A mini terminal game package with Tic-Tac-Toe
Home-page: https://github.com/yourusername/pynexitec
Author: Aayush B
Author-email: your.email@example.com
Classifier: Programming Language :: Python :: 3
Classifier: License :: OSI Approved :: MIT License
Classifier: Operating System :: OS Independent
Requires-Python: >=3.7
License-File: LICENSE
Dynamic: author
Dynamic: author-email
Dynamic: classifier
Dynamic: description-content-type
Dynamic: home-page
Dynamic: license-file
Dynamic: requires-python
Dynamic: summary
